delayedarray/BinaryIsometricOp.py
delayedarray/Cast.py
delayedarray/Combine.py
delayedarray/DelayedArray.py
delayedarray/DelayedOp.py
delayedarray/Grid.py
delayedarray/RegularTicks.py
delayedarray/Round.py
delayedarray/SparseNdarray.py
delayedarray/Subset.py
delayedarray/Transpose.py
delayedarray/UnaryIsometricOpSimple.py
delayedarray/UnaryIsometricOpWithArgs.py
delayedarray/__init__.py
delayedarray/_isometric.py
delayedarray/_mask.py
delayedarray/_statistics.py
delayedarray/_subset.py
delayedarray/apply_over_blocks.py
delayedarray/apply_over_dimension.py
delayedarray/chunk_grid.py
delayedarray/create_dask_array.py
delayedarray/default_buffer_size.py
delayedarray/extract_dense_array.py
delayedarray/extract_sparse_array.py
delayedarray/is_masked.py
delayedarray/is_pristine.py
delayedarray/is_sparse.py
delayedarray/to_dense_array.py
delayedarray/to_scipy_sparse_matrix.py
delayedarray/to_sparse_array.py
delayedarray/wrap.py
delayedarray-0.6.2.dist-info/licenses/LICENSE.txt
delayedarray-0.6.2.dist-info/METADATA
delayedarray-0.6.2.dist-info/WHEEL
delayedarray-0.6.2.dist-info/top_level.txt
delayedarray-0.6.2.dist-info/RECORD
