Metadata-Version: 2.4
Name: DelayedArray
Version: 0.6.2
Summary: Delayed array operations from Bioconductor
Home-page: https://github.com/biocpy/DelayedArray
Author: Aaron Lun
Author-email: infinite.monkeys.with.keyboards@gmail.com
License: MIT
Project-URL: Documentation, https://biocpy.github.io/DelayedArray/
Platform: any
Classifier: Development Status :: 4 - Beta
Classifier: Programming Language :: Python
Requires-Python: >=3.9
License-File: LICENSE.txt
Requires-Dist: importlib-metadata; python_version < "3.8"
Requires-Dist: numpy
Requires-Dist: biocutils>=0.1.8
Provides-Extra: dask
Requires-Dist: dask; extra == "dask"
Provides-Extra: testing
Requires-Dist: setuptools; extra == "testing"
Requires-Dist: pytest; extra == "testing"
Requires-Dist: pytest-cov; extra == "testing"
Requires-Dist: scipy; extra == "testing"
Dynamic: license-file
